pyZZUF/__init__.py
pyZZUF/pyZZUF.py
pyZZUF-0.1.dist-info/METADATA
pyZZUF-0.1.dist-info/WHEEL
pyZZUF-0.1.dist-info/top_level.txt
pyZZUF-0.1.dist-info/RECORD
